README.rst
setup.py
code2html/__init__.py
code2html/args.py
code2html/cli.py
code2html/core.py
code2html/ignores.py
code2html/util.py
code2html/vim.py
code2html.egg-info/PKG-INFO
code2html.egg-info/SOURCES.txt
code2html.egg-info/dependency_links.txt
code2html.egg-info/entry_points.txt
code2html.egg-info/requires.txt
code2html.egg-info/top_level.txt