Metadata-Version: 1.1
Name: code2html
Version: 0.3.2
Summary: Convert source code repository to HTML files, with beautiful syntax highlight.
Home-page: https://github.com/kfei/code2html
Author: Lin, Ke-fei
Author-email: kfei@kfei.net
License: MIT
Keywords: code,syntax,highlight,convert,html
Platform: UNKNOWN
Classifier: Development Status :: 5 - Production/Stable
Classifier: Intended Audience :: Developers
Classifier: License :: OSI Approved :: MIT License
Classifier: Topic :: Utilities
Classifier: Operating System :: OS Independent
Classifier: Programming Language :: Python :: 2.6
Classifier: Programming Language :: Python :: 2.7
Classifier: Programming Language :: Python :: 3.3
